<?xml version="1.0" encoding="utf-8"?>
<clothing-items>
 <clothing>
  <id>
   312744930
  </id>
  <name>
   Lacoste Hat O-8133
  </name>
  <category>
   Hat
  </category>
  <size>
   L
  </size>
  <color>
   Синий
  </color>
  <material>
   Шелк
  </material>
  <price>
   809249
  </price>
  <rating>
   2.59
  </rating>
  <reviews>
   231363
  </reviews>
  <exclusive>
   no
  </exclusive>
  <sporty>
   no
  </sporty>
 </clothing>
 <clothing>
  <id>
   295578240
  </id>
  <name>
   Converse Umbrellas T-6795
  </name>
  <category>
   Umbrellas
  </category>
  <size>
   M
  </size>
  <color>
   Красный
  </color>
  <material>
   Вискоза
  </material>
  <price>
   690186
  </price>
  <rating>
   3.17
  </rating>
  <reviews>
   576253
  </reviews>
  <sporty>
   no
  </sporty>
 </clothing>
 <clothing>
  <id>
   352954416
  </id>
  <name>
   Adidas Blouse T-5494
  </name>
  <category>
   Blouse
  </category>
  <size>
   S
  </size>
  <color>
   Красный
  </color>
  <material>
   Нейлон
  </material>
  <price>
   974960
  </price>
  <rating>
   3.69
  </rating>
  <reviews>
   308938
  </reviews>
 </clothing>
 <clothing>
  <id>
   391552988
  </id>
  <name>
   Lacoste Shoes M-9982
  </name>
  <category>
   Shoes
  </category>
  <size>
   L
  </size>
  <color>
   Фиолетовый
  </color>
  <material>
   Хлопок
  </material>
  <price>
   408260
  </price>
  <rating>
   4.02
  </rating>
  <reviews>
   574637
  </reviews>
 </clothing>
 <clothing>
  <id>
   282512235
  </id>
  <name>
   Lacoste T-shirt Z-8904
  </name>
  <category>
   T-shirt
  </category>
  <size>
   XL
  </size>
  <color>
   Оранжевый
  </color>
  <material>
   Кожа
  </material>
  <price>
   427093
  </price>
  <rating>
   4.14
  </rating>
  <reviews>
   855728
  </reviews>
  <sporty>
   no
  </sporty>
 </clothing>
 <clothing>
  <id>
   408777526
  </id>
  <name>
   Lacoste Handbags S-5899
  </name>
  <category>
   Handbags
  </category>
  <size>
   L
  </size>
  <color>
   Желтый
  </color>
  <material>
   Шерсть
  </material>
  <price>
   278062
  </price>
  <rating>
   4.84
  </rating>
  <reviews>
   780960
  </reviews>
  <exclusive>
   yes
  </exclusive>
  <sporty>
   yes
  </sporty>
 </clothing>
 <clothing>
  <id>
   404739359
  </id>
  <name>
   Converse Pants P-9102
  </name>
  <category>
   Pants
  </category>
  <size>
   M
  </size>
  <color>
   Оранжевый
  </color>
  <material>
   Нейлон
  </material>
  <price>
   813397
  </price>
  <rating>
   2.98
  </rating>
  <reviews>
   519539
  </reviews>
  <new>
   +
  </new>
  <sporty>
   no
  </sporty>
 </clothing>
 <clothing>
  <id>
   674764720
  </id>
  <name>
   Vans T-shirt W-4643
  </name>
  <category>
   T-shirt
  </category>
  <size>
   L
  </size>
  <color>
   Зеленый
  </color>
  <material>
   Кожа
  </material>
  <price>
   145497
  </price>
  <rating>
   3.77
  </rating>
  <reviews>
   222616
  </reviews>
  <new>
   -
  </new>
  <sporty>
   no
  </sporty>
 </clothing>
 <clothing>
  <id>
   145447045
  </id>
  <name>
   Ellesse Shoes J-8403
  </name>
  <category>
   Shoes
  </category>
  <size>
   XXL
  </size>
  <color>
   Фиолетовый
  </color>
  <material>
   Полиэстер
  </material>
  <price>
   821236
  </price>
  <rating>
   4.18
  </rating>
  <reviews>
   977395
  </reviews>
  <new>
   -
  </new>
 </clothing>
 <clothing>
  <id>
   658279114
  </id>
  <name>
   Lacoste T-shirt R-3738
  </name>
  <category>
   T-shirt
  </category>
  <size>
   S
  </size>
  <color>
   Фиолетовый
  </color>
  <material>
   Шелк
  </material>
  <price>
   169331
  </price>
  <rating>
   3.04
  </rating>
  <reviews>
   412172
  </reviews>
  <exclusive>
   no
  </exclusive>
  <sporty>
   yes
  </sporty>
 </clothing>
 <clothing>
  <id>
   151291540
  </id>
  <name>
   Fila Sweater E-7346
  </name>
  <category>
   Sweater
  </category>
  <size>
   XXL
  </size>
  <color>
   Фиолетовый
  </color>
  <material>
   Нейлон
  </material>
  <price>
   227926
  </price>
  <rating>
   1.05
  </rating>
  <reviews>
   922019
  </reviews>
  <exclusive>
   no
  </exclusive>
  <sporty>
   no
  </sporty>
 </clothing>
 <clothing>
  <id>
   241004572
  </id>
  <name>
   Under Armour Skirt J-6357
  </name>
  <category>
   Skirt
  </category>
  <size>
   XXL
  </size>
  <color>
   Голубой
  </color>
  <material>
   Полиэстер
  </material>
  <price>
   408271
  </price>
  <rating>
   1.14
  </rating>
  <reviews>
   860957
  </reviews>
  <exclusive>
   no
  </exclusive>
  <sporty>
   no
  </sporty>
 </clothing>
 <clothing>
  <id>
   351308785
  </id>
  <name>
   Under Armour Blouse S-8027
  </name>
  <category>
   Blouse
  </category>
  <size>
   XXL
  </size>
  <color>
   Фиолетовый
  </color>
  <material>
   Шелк
  </material>
  <price>
   247134
  </price>
  <rating>
   1.52
  </rating>
  <reviews>
   845418
  </reviews>
  <sporty>
   no
  </sporty>
 </clothing>
 <clothing>
  <id>
   573372548
  </id>
  <name>
   Lacoste Sweater F-8674
  </name>
  <category>
   Sweater
  </category>
  <size>
   L
  </size>
  <color>
   Оранжевый
  </color>
  <material>
   Шелк
  </material>
  <price>
   833497
  </price>
  <rating>
   3.33
  </rating>
  <reviews>
   916781
  </reviews>
  <sporty>
   no
  </sporty>
 </clothing>
 <clothing>
  <id>
   621840386
  </id>
  <name>
   Ellesse Socks X-4001
  </name>
  <category>
   Socks
  </category>
  <size>
   S
  </size>
  <color>
   Голубой
  </color>
  <material>
   Полиэстер
  </material>
  <price>
   941910
  </price>
  <rating>
   1.77
  </rating>
  <reviews>
   263595
  </reviews>
  <exclusive>
   yes
  </exclusive>
  <sporty>
   yes
  </sporty>
 </clothing>
 <clothing>
  <id>
   627550142
  </id>
  <name>
   Converse Jacket S-8197
  </name>
  <category>
   Jacket
  </category>
  <size>
   XXL
  </size>
  <color>
   Желтый
  </color>
  <material>
   Шелк
  </material>
  <price>
   464998
  </price>
  <rating>
   2.93
  </rating>
  <reviews>
   150239
  </reviews>
  <new>
   -
  </new>
  <sporty>
   no
  </sporty>
 </clothing>
 <clothing>
  <id>
   104699668
  </id>
  <name>
   Brooks Gloves O-7387
  </name>
  <category>
   Gloves
  </category>
  <size>
   M
  </size>
  <color>
   Синий
  </color>
  <material>
   Лен
  </material>
  <price>
   525436
  </price>
  <rating>
   4.59
  </rating>
  <reviews>
   827750
  </reviews>
  <new>
   +
  </new>
 </clothing>
 <clothing>
  <id>
   513773939
  </id>
  <name>
   DC Dress E-5355
  </name>
  <category>
   Dress
  </category>
  <size>
   XL
  </size>
  <color>
   Оранжевый
  </color>
  <material>
   Лен
  </material>
  <price>
   827467
  </price>
  <rating>
   2.12
  </rating>
  <reviews>
   223032
  </reviews>
  <new>
   +
  </new>
  <exclusive>
   no
  </exclusive>
 </clothing>
 <clothing>
  <id>
   538647555
  </id>
  <name>
   Asics Belts K-7251
  </name>
  <category>
   Belts
  </category>
  <size>
   S
  </size>
  <color>
   Фиолетовый
  </color>
  <material>
   Лен
  </material>
  <price>
   974284
  </price>
  <rating>
   2.24
  </rating>
  <reviews>
   798126
  </reviews>
  <exclusive>
   yes
  </exclusive>
  <sporty>
   no
  </sporty>
 </clothing>
 <clothing>
  <id>
   918199448
  </id>
  <name>
   New Balance Skirt Q-6573
  </name>
  <category>
   Skirt
  </category>
  <size>
   S
  </size>
  <color>
   Красный
  </color>
  <material>
   Шелк
  </material>
  <price>
   679145
  </price>
  <rating>
   3.79
  </rating>
  <reviews>
   79014
  </reviews>
  <new>
   +
  </new>
  <sporty>
   no
  </sporty>
 </clothing>
 <clothing>
  <id>
   606150582
  </id>
  <name>
   DC Jeans N-8511
  </name>
  <category>
   Jeans
  </category>
  <size>
   XL
  </size>
  <color>
   Голубой
  </color>
  <material>
   Шелк
  </material>
  <price>
   371855
  </price>
  <rating>
   2.51
  </rating>
  <reviews>
   599685
  </reviews>
  <sporty>
   no
  </sporty>
 </clothing>
 <clothing>
  <id>
   934141800
  </id>
  <name>
   Addidas Dress C-3587
  </name>
  <category>
   Dress
  </category>
  <size>
   L
  </size>
  <color>
   Зеленый
  </color>
  <material>
   Полиэстер
  </material>
  <price>
   859486
  </price>
  <rating>
   3.65
  </rating>
  <reviews>
   898234
  </reviews>
  <new>
   -
  </new>
  <sporty>
   no
  </sporty>
 </clothing>
 <clothing>
  <id>
   848485357
  </id>
  <name>
   New Balance Skirt X-1097
  </name>
  <category>
   Skirt
  </category>
  <size>
   XXL
  </size>
  <color>
   Фиолетовый
  </color>
  <material>
   Лен
  </material>
  <price>
   864499
  </price>
  <rating>
   2.55
  </rating>
  <reviews>
   524337
  </reviews>
  <new>
   -
  </new>
  <sporty>
   no
  </sporty>
 </clothing>
 <clothing>
  <id>
   250995199
  </id>
  <name>
   Converse Skirt A-4798
  </name>
  <category>
   Skirt
  </category>
  <size>
   S
  </size>
  <color>
   Синий
  </color>
  <material>
   Лен
  </material>
  <price>
   135426
  </price>
  <rating>
   3.29
  </rating>
  <reviews>
   296384
  </reviews>
  <new>
   -
  </new>
  <sporty>
   no
  </sporty>
 </clothing>
 <clothing>
  <id>
   405684660
  </id>
  <name>
   Vans Hat W-5434
  </name>
  <category>
   Hat
  </category>
  <size>
   XXL
  </size>
  <color>
   Синий
  </color>
  <material>
   Кожа
  </material>
  <price>
   786344
  </price>
  <rating>
   4.04
  </rating>
  <reviews>
   127467
  </reviews>
  <new>
   -
  </new>
  <sporty>
   no
  </sporty>
 </clothing>
 <clothing>
  <id>
   320624770
  </id>
  <name>
   Asics Jeans U-1662
  </name>
  <category>
   Jeans
  </category>
  <size>
   L
  </size>
  <color>
   Синий
  </color>
  <material>
   Кожа
  </material>
  <price>
   629381
  </price>
  <rating>
   4.61
  </rating>
  <reviews>
   229967
  </reviews>
  <new>
   +
  </new>
  <sporty>
   yes
  </sporty>
 </clothing>
 <clothing>
  <id>
   970207341
  </id>
  <name>
   Lacoste Belts V-1189
  </name>
  <category>
   Belts
  </category>
  <size>
   XXL
  </size>
  <color>
   Голубой
  </color>
  <material>
   Шелк
  </material>
  <price>
   888320
  </price>
  <rating>
   1.91
  </rating>
  <reviews>
   638737
  </reviews>
  <exclusive>
   no
  </exclusive>
 </clothing>
 <clothing>
  <id>
   823829084
  </id>
  <name>
   Vans Blouse L-9273
  </name>
  <category>
   Blouse
  </category>
  <size>
   S
  </size>
  <color>
   Голубой
  </color>
  <material>
   Шелк
  </material>
  <price>
   882221
  </price>
  <rating>
   2.26
  </rating>
  <reviews>
   178278
  </reviews>
  <new>
   -
  </new>
  <sporty>
   no
  </sporty>
 </clothing>
</clothing-items>
